diff_decorator/__init__.py
diff_decorator/diff_with.py
diff_decorator-0.3.0.dist-info/LICENSE
diff_decorator-0.3.0.dist-info/METADATA
diff_decorator-0.3.0.dist-info/WHEEL
diff_decorator-0.3.0.dist-info/top_level.txt
diff_decorator-0.3.0.dist-info/RECORD
