Metadata-Version: 2.1
Name: diff-decorator
Version: 0.3.0
Summary: A decorator for diffing outputs in Python tests
Home-page: https://github.com/weshouman/py-diff-decorator
Author: Walid Shouman
Author-email: eng.walidshouman@gmail.com
Classifier: Programming Language :: Python :: 3
Classifier: License :: OSI Approved :: MIT License
Classifier: Operating System :: OS Independent
License-File: LICENSE
